README.md
setup.py
AlbertMarker.egg-info/PKG-INFO
AlbertMarker.egg-info/SOURCES.txt
AlbertMarker.egg-info/dependency_links.txt
AlbertMarker.egg-info/requires.txt
AlbertMarker.egg-info/top_level.txt
marker/__init__.py
marker/config.py
marker/marker.py
marker/utils.py