Metadata-Version: 2.1
Name: AlbertMarker
Version: 0.0.1
Summary: Terry Marker
Home-page: https://github.com/napoler/AlBert-BiLSTM-CRF-pytorch
Author: Terry Chan
Author-email: napoler2008@gmail.com
License: UNKNOWN
Platform: UNKNOWN
